dictionary/__init__.py
dictionary/dictionary.py
mannan_abdul_very_simple_dictionary-2.1.0.dist-info/METADATA
mannan_abdul_very_simple_dictionary-2.1.0.dist-info/WHEEL
mannan_abdul_very_simple_dictionary-2.1.0.dist-info/top_level.txt
mannan_abdul_very_simple_dictionary-2.1.0.dist-info/RECORD
