Metadata-Version: 2.1
Name: mannan-abdul-very-simple-dictionary
Version: 2.1.0
Summary: UNKNOWN
Author: Mannan Abdul
License: UNKNOWN
Platform: UNKNOWN
Requires-Python: >=3.8
Requires-Dist: requests (>=2.23.0)
